ftuutils/__init__.py
ftuutils/base.py
ftuutils/codegenerationutils.py
ftuutils/compositionutils.py
ftuutils/graphutils.py
ftuutils/latexgenerationutils.py
ftuutils/phsutils.py
ftuutils/runsimulations.py
ftuutils/simulationutils.py
ftuutils/sympyutils.py
ftuutils/templates/Neuman2DirichletMLPDDEC.pyt
ftuutils/templates/Neuman2DirichletSRDDEC.pyt
ftuutils/templates/NeuralOp.pyt
ftuutils/templates/hamexpression.pyt
ftuutils/templates/hamlettemplate.pyt
ftuutils/templates/hammlpexpression.pyt
ftuutils/templates/hamsrexpression.pyt
ftuutils/templates/runsimulations.pyt
ftuutils/templates/state2hamiltonianmap.pyt
ftuutils/templates/state2hamiltonianmlpmap.pyt
ftuutils/templates/state2hamiltoniansrmap.pyt
ftuutils-0.1.4.dist-info/LICENSE
ftuutils-0.1.4.dist-info/METADATA
ftuutils-0.1.4.dist-info/WHEEL
ftuutils-0.1.4.dist-info/top_level.txt
ftuutils-0.1.4.dist-info/RECORD
