Metadata-Version: 2.1
Name: ftuutils
Version: 0.1.4
Summary: Utilities to create FTU graph templates
Author-email: "Jagir R. Hussan" <r.jagir@auckland.ac.nz>
License: MIT License
Keywords: FTU,Tissue,Cells,Port-Hamiltonian,Bond Graphs,12 Labours
Classifier: Programming Language :: Python :: 3
Classifier: License :: OSI Approved :: MIT License
Classifier: Operating System :: OS Independent
Requires-Python: >=3.7
License-File: LICENSE
